{
    "name": "Beach start",
    "youTubeLinkExample1": "https://www.youtube.com/watch?v=XmKH-qBYEF8",
    "youTubeLinkExample2": "https://www.youtube.com/watch?v=msv3B6vAWWo",
    "complexity": "Easy",
    "requiredSpeed": "Slow"
}
{
    "name": "Water start",
    "youTubeLinkExample1": "https://www.youtube.com/watch?v=QmWnEZ-G-HE",
    "youTubeLinkExample2": "https://www.youtube.com/watch?v=sMTbyOjVTHQ",
    "complexity": "Medium",
    "requiredSpeed": "Slow"
}
{
    "name": "Heli Tack",
    "youTubeLinkExample1": "https://www.youtube.com/watch?v=3w803yCuuqQ",
    "youTubeLinkExample2": "https://www.youtube.com/watch?v=jp0WpPo4QcA",
    "complexity": "Medium",
    "requiredSpeed": "Slow"
}
{
    "name": "Carve Tack",
    "youTubeLinkExample1": "https://www.youtube.com/watch?v=mIeJqwjHaZw",
    "youTubeLinkExample2": "https://www.youtube.com/watch?v=50V1WFmrhG8",
    "complexity": "Complex",
    "requiredSpeed": "Fast"
}
{
    "name": "Duck jibe",
    "youTubeLinkExample1": "https://www.youtube.com/watch?v=mIeJqwjHaZw",
    "youTubeLinkExample2": "https://www.youtube.com/watch?v=f1J2TI2tCqA",
    "complexity": "Complex",
    "requiredSpeed": "Fast"
}
{
    "name":"Harness Use",
    "youTubeLinkExample1": "https://www.youtube.com/watch?v=BhWBvFAI99A",
    "youTubeLinkExample2": "https://www.youtube.com/watch?v=yfTNYs1mBPg",
    "complexity": "Medium",
    "requiredSpeed": "Medium"
}
{
    "name":"Non Planing Gybe",
    "youTubeLinkExample1": "https://www.youtube.com/watch?v=jHhiaW9Iwc4",
    "youTubeLinkExample2": "https://www.youtube.com/watch?v=KXjq9cpHrU4",
    "complexity": "Medium",
    "requiredSpeed": "Medium"
}
{
    "name":"Forward Loop",
    "youTubeLinkExample1": "https://www.youtube.com/watch?v=SCvhi7aE4MQ",
    "youTubeLinkExample2": "https://www.youtube.com/watch?v=Jv3vXQ480rE",
    "complexity": "Complex",
    "requiredSpeed": "Fast"
}
{
    "name":"Flaka",
    "youTubeLinkExample1": "https://www.youtube.com/watch?v=jeSiLUqr7KA",
    "youTubeLinkExample2": "https://www.youtube.com/watch?v=0n7hR4dclhY",
    "complexity": "Complex",
    "requiredSpeed": "Fast"
}
{
    "name":"Vulcan",
    "youTubeLinkExample1": "https://www.youtube.com/watch?v=1EVWzf9Lh6Q",
    "youTubeLinkExample2": "https://www.youtube.com/watch?v=7xnwE0aWFSI",
    "complexity": "Complex",
    "requiredSpeed": "Fast"
}
